Workbook

Sheet Sprints
A1: Sprint Planning por Casos de Uso · Area Tecnica
A2: 6 integrantes · 4 sprints de 20 dias · 26/08/2026 a 13/11/2026 · modelo hibrido: carril Plataforma + 2 parejas de Producto
A4: Sprint ID | B4: Sprint | C4: Fecha Inicio | D4: Fecha Fin | E4: Modelo | F4: Objetivo | G4: Entregables
A5: S1 | B5: Cimientos y acceso | C5: 46260 | D5: 46279 | E5: Horizontal: todos por tecnologia | F5: Aprender el stack, congelar los contratos de API y dejar el paquete de Seguridad funcionando de punta a punta en las tres plataformas. | G5: Contrato OpenAPI congelado; mocks operativos; Docker Compose; CI/CD a staging; CU-01 a CU-05 completos en Backend, Web y Movil.
A6: S2 | B6: Plantel, partidos y calibracion | C6: 46280 | D6: 46299 | E6: Hibrido: 2 Plataforma + 2 parejas | F6: Las dos parejas se apropian de los casos de uso de Gestion Deportiva de punta a punta, mientras Plataforma resuelve calibracion y tiempo real. | G6: CU-09 a CU-17 completos en las tres capas; CU-18 a CU-23 de calibracion; hub de WebSockets y emisor simulado.
A7: S3 | B7: Partido en vivo y metricas | C7: 46300 | D7: 46319 | E7: Hibrido: 2 Plataforma + 2 parejas | F7: El worker de vision alimenta el sistema y las parejas construyen la operacion del partido y el analisis tactico completos. | G7: CU-24 a CU-29 de vision; CU-30 a CU-39 de operacion; CU-40 a CU-46 de analisis, cada uno en sus tres capas.
A8: S4 | B8: Asistencia al DT, integracion y cierre | C8: 46320 | D8: 46339 | E8: Hibrido + cierre conjunto | F8: Completar la capa de asistencia al entrenador y dejar el sistema integrado, probado en cancha real y desplegado. Desarrollo hasta el 04/11, estabilizacion del 05/11 al 13/11. | G8: CU-49 a CU-58 completos; pruebas extremo a extremo; prueba en partido real; criterios de calidad medidos; despliegue y demostracion.
A10: Como se organiza el trabajo
A11: · CARRIL PLATAFORMA (2 personas, rotando): contratos, autenticacion, multi-tenant, WebSockets, worker de vision y calibracion. Es trabajo horizontal porque no se puede rebanar por caso de uso.
A12: · CARRIL PRODUCTO (4 personas en 2 parejas): cada pareja se apropia de casos de uso completos y los lleva de la base de datos a la API, a la Web y al Movil. Sin entregas entre personas.
A13: · El Sprint 1 es horizontal para todos: los cimientos lo son por naturaleza, y nadie puede tomar una rebanada en Flutter si nunca escribio Dart.
A14: · Dentro de cada pareja, uno toma Backend y Web y el otro Movil; en el sprint siguiente invierten. Se sientan al lado: no se entregan trabajo, son duenos del caso de uso juntos.

Sheet Sprint Planning
A1: Task ID | B1: Sprint | C1: Carril | D1: Integrante | E1: Caso de Uso | F1: Nombre de Tarea | G1: Descripcion | H1: Tecnologia | I1: Prioridad | J1: Fecha Inicio | K1: Fecha Limite | L1: Dependencia | M1: Estado | N1: Criterio de Finalizacion
A2: T-001 | B2: S1 | C2: Plataforma | D2: Daniel | E2: — | F2: Contratos OpenAPI de los 6 paquetes | G2: Definir y congelar el esquema OpenAPI completo: rutas, DTOs, codigos de error y ejemplos. Es el insumo del que dependen Web y Movil para no bloquearse. | H2: Backend | I2: Alta | J2: 46260 | K2: 46264 | L2: - | M2: Pendiente | N2: Esquema validado, revisado por un integrante de Web y uno de Movil, y mergeado a main.
A3: T-002 | B3: S1 | C3: Plataforma | D3: Daniel | E3: — | F3: Modelos base y migraciones | G3: Modelos club y usuario con SQLAlchemy, Alembic configurado y migracion inicial generada. | H3: Backend | I3: Alta | J3: 46264 | K3: 46268 | L3: T-001 | M3: Pendiente | N3: Migracion aplicada sin errores en base limpia y revertible con downgrade.
A4: T-003 | B4: S1 | C4: Plataforma | D4: Daniel | E4: CU-01 | F4: Registrar club y cuenta administradora | G4: Endpoint de alta de club con su primer usuario ADMIN y hash de contrasena con bcrypt. | H4: Backend | I4: Alta | J4: 46268 | K4: 46271 | L4: T-002 | M4: Pendiente | N4: Registro devuelve sesion iniciada; email duplicado responde 409.
A5: T-004 | B5: S1 | C5: Plataforma | D5: Daniel | E5: CU-02, CU-03 | F5: Login, logout y refresco de token | G5: Autenticacion JWT con token de acceso de 15 min, refresco de 30 dias con rotacion y lista negra al cerrar sesion. | H5: Backend | I5: Alta | J5: 46271 | K5: 46275 | L5: T-003 | M5: Pendiente | N5: Credenciales invalidas responden 401 generico; el refresh invalidado deja de servir.
A6: T-005 | B6: S1 | C6: Plataforma | D6: Daniel | E6: CU-04 | F6: Gestionar usuarios y roles | G6: ABM de usuarios del club con los cuatro roles y control de acceso por rol. | H6: Backend | I6: Alta | J6: 46275 | K6: 46279 | L6: T-004 | M6: Pendiente | N6: Un ASISTENTE recibe 403 al intentar modificar el plantel.
A7: T-006 | B7: S1 | C7: Plataforma | D7: Susana | E7: — | F7: Docker Compose del entorno | G7: API, PostgreSQL y Redis con un solo comando, con migraciones y datos de prueba en el primer arranque. | H7: Backend | I7: Alta | J7: 46260 | K7: 46264 | L7: - | M7: Pendiente | N7: Un integrante que no lo escribio levanta el entorno siguiendo solo el README.
A8: T-007 | B8: S1 | C8: Plataforma | D8: Susana | E8: — | F8: Integracion continua | G8: Lint, verificacion de tipos y suite de pruebas en cada Pull Request, bloqueando el merge si falla. | H8: Backend | I8: Alta | J8: 46264 | K8: 46268 | L8: T-006 | M8: Pendiente | N8: Un PR con pruebas en rojo queda bloqueado y el estado es visible en el PR.
A9: T-008 | B9: S1 | C9: Plataforma | D9: Susana | E9: — | F9: Despliegue automatico a staging | G9: Al integrar a main se despliega API y web en menos de 10 minutos, con migraciones automaticas. | H9: Backend | I9: Alta | J9: 46268 | K9: 46271 | L9: T-007 | M9: Pendiente | N9: Un merge a main queda accesible por URL; un fallo notifica al canal del equipo.
A10: T-009 | B10: S1 | C10: Plataforma | D10: Susana | E10: — | F10: Aislamiento multi-club | G10: Filtro por club en un manager base compartido, usado por todas las consultas del sistema. | H10: Backend | I10: Alta | J10: 46271 | K10: 46275 | L10: T-002 | M10: Pendiente | N10: Ninguna consulta puede omitir el filtro: esta centralizado en core/tenancy.py.
A11: T-010 | B11: S1 | C11: Plataforma | D11: Susana | E11: — | F11: Prueba de acceso cruzado entre clubes | G11: Prueba automatizada que verifica que un club no accede a recursos de otro, en todos los endpoints. | H11: Backend | I11: Alta | J11: 46275 | K11: 46279 | L11: T-009 | M11: Pendiente | N11: Un usuario del club A recibe 404 al pedir un recurso del club B; corre en cada CI.
A12: T-011 | B12: S1 | C12: Producto · P1 | D12: Jhon | E12: — | F12: Andamiaje de la aplicacion web | G12: React 19 + TypeScript + Vite con estructura por features, alias de importacion y linter. | H12: Web | I12: Alta | J12: 46260 | K12: 46265 | L12: - | M12: Pendiente | N12: npm run build en verde y estructura documentada en el README.
A13: T-012 | B13: S1 | C13: Producto · P1 | D13: Jhon | E13: — | F13: Servidor de mocks desde el OpenAPI | G13: Mock generado del esquema para que Web y Movil desarrollen sin esperar al backend. Pieza clave anti-bloqueo. | H13: Web | I13: Alta | J13: 46265 | K13: 46270 | L13: T-001 | M13: Pendiente | N13: Web y Movil consumen datos simulados de los 6 paquetes cambiando una variable de entorno.
... A109: T-108 | B109: S4 | C109: Plataforma | D109: Susana | E109: — | F109: Sprint Review final y retrospectiva | G109: Demostracion del incremento completo, aceptacion del Product Owner y retrospectiva del proyecto. | H109: Integracion | I109: Alta | J109: 46336 | K109: 46339 | L109: T-088 | M109: Pendiente | N109: El Product Owner acepta el incremento y la retrospectiva queda documentada.

Sheet Casos de Uso
A1: Mapa de apropiacion: quien es dueno de cada caso de uso
A2: Cada caso de uso tiene duenos con nombre y apellido que lo llevan de la base de datos a la pantalla. Si falta una capa, el caso de uso no esta terminado.
A4: Caso de Uso | B4: Paquete | C4: Nombre | D4: Sprint | E4: Carril | F4: Duenos | G4: Tareas | H4: Capas cubiertas
A5: CU-01 | B5: P1 | C5: Registrar club y cuenta administradora | D5: S1 | E5: Plataforma, Producto · P1 | F5: Daniel, Jhon | G5: T-003, T-014 | H5: Backend · Web
A6: CU-02 | B6: P1 | C6: Iniciar sesion | D6: S1 | E6: Plataforma, Producto · P1, Producto · P2 | F6: Alex, Daniel, Jhon | G6: T-004, T-013, T-021 | H6: Backend · Movil · Web
A7: CU-03 | B7: P1 | C7: Cerrar sesion | D7: S1 | E7: Plataforma, Producto · P2 | F7: Alex, Daniel | G7: T-004, T-022 | H7: Backend · Movil
A8: CU-04 | B8: P1 | C8: Gestionar usuarios y roles | D8: S1 | E8: Plataforma, Producto · P1 | F8: Alejandra, Daniel | G8: T-005, T-017 | H8: Backend · Web
A9: CU-05 | B9: P1 | C9: Administrar perfil propio | D9: S1 | E9: Producto · P1, Producto · P2 | F9: Alejandra, Araceli | G9: T-018, T-025 | H9: Movil · Web
A10: CU-09 | B10: P2 | C10: Gestionar equipos | D10: S2 | E10: Producto · P1 | F10: Daniel | G10: T-037, T-041, T-044 | H10: Backend · Movil · Web
A11: CU-10 | B11: P2 | C11: Registrar indumentaria del equipo | D11: S2 | E11: Producto · P1 | F11: Daniel | G11: T-038, T-041 | H11: Backend · Web
A12: CU-11 | B12: P2 | C12: Gestionar jugadores | D12: S2 | E12: Producto · P1 | F12: Alex | G12: T-039, T-042, T-045 | H12: Backend · Movil · Web
A13: CU-12 | B13: P2 | C13: Importar plantel desde archivo | D13: S2 | E13: Producto · P1 | F13: Alex | G13: T-040, T-043 | H13: Backend · Web
A14: CU-13 | B14: P2 | C14: Gestionar competiciones | D14: S2 | E14: Producto · P2 | F14: Susana | G14: T-046 | H14: Backend
A15: CU-14 | B15: P2 | C15: Programar partido | D15: S2 | E15: Producto · P2 | F15: Susana | G15: T-047, T-049 | H15: Backend · Web
... A56: CU-56 | B56: P6 | C56: Exportar metricas | D56: S4 | E56: Producto · P2 | F56: Jhon | G56: T-099 | H56: Backend
A59: 52 casos de uso cubiertos. Verde = las 3 capas (Backend, Web y Movil); azul = 2 capas; gris = 1 capa.

Sheet Distribucion Equipo
A1: Carriles, parejas y rotacion tecnologica
A2: Nadie repite pareja y los seis pasan por el carril de Plataforma. Cada integrante trabaja en Backend, Web y Movil a lo largo del proyecto.
A4: Integrante | B4: S1 · Cimientos y acceso | C4: S2 · Plantel, partidos y ca | D4: S3 · Partido en vivo y metr | E4: S4 · Asistencia al DT, inte | F4: Backend | G4: Web | H4: Movil | I4: Integr. | J4: QA | K4: Total
A5: Daniel | B5: Plataforma Backend | C5: Producto · P1 Backend, Web | D5: Producto · P2 Web, Movil | E5: Plataforma Backend, Integracion | F5: 9 | G5: 4 | H5: 2 | I5: 2 | J5: 1 | K5: 18
A6: Jhon | B6: Producto · P1 Web | C6: Plataforma Web, Backend | D6: Producto · P1 Backend, Web | E6: Producto · P2 Backend, Web | F6: 6 | G6: 10 | H6: 2 | I6: 0 | J6: 0 | K6: 18
A7: Susana | B7: Plataforma Backend | C7: Producto · P2 Backend, Web | D7: Producto · P1 Movil, Backend | E7: Plataforma Integracion, Backend | F7: 10 | G7: 3 | H7: 3 | I7: 3 | J7: 1 | K7: 20
A8: Alex | B8: Producto · P2 Movil | C8: Producto · P1 Backend, Web | D8: Plataforma Backend | E8: Producto · P2 Web, Integracion | F8: 7 | G8: 4 | H8: 5 | I8: 1 | J8: 1 | K8: 18
A9: Alejandra | B9: Producto · P1 Web | C9: Plataforma Backend | D9: Producto · P2 Backend, Movil | E9: Producto · P1 Web, QA | F9: 8 | G9: 6 | H9: 2 | I9: 0 | J9: 1 | K9: 17
A10: Araceli | B10: Producto · P2 Movil | C10: Producto · P2 Movil, Backend | D10: Plataforma Backend, Web | E10: Producto · P1 Movil, Web | F10: 4 | G10: 4 | H10: 8 | I10: 0 | J10: 1 | K10: 17
A13: Parejas por sprint
A14: Sprint | B14: Carril | C14: Integrantes
A15: S1 | B15: Plataforma | C15: Daniel, Susana
A16: S1 | B16: Producto · P1 | C16: Alejandra, Jhon
A17: S1 | B17: Producto · P2 | C17: Alex, Araceli
A18: S2 | B18: Plataforma | C18: Alejandra, Jhon
A19: S2 | B19: Producto · P1 | C19: Alex, Daniel
A20: S2 | B20: Producto · P2 | C20: Araceli, Susana
A21: S3 | B21: Plataforma | C21: Alex, Araceli
A22: S3 | B22: Producto · P1 | C22: Jhon, Susana
A23: S3 | B23: Producto · P2 | C23: Alejandra, Daniel
A24: S4 | B24: Plataforma | C24: Daniel, Susana
A25: S4 | B25: Producto · P1 | C25: Alejandra, Araceli
A26: S4 | B26: Producto · P2 | C26: Alex, Jhon

Sheet Dependencias
A1: Dependencias y estrategias anti-bloqueo
A2: 28 dependencias cruzadas sobre 108 tareas, pero solo 9 atraviesan una frontera organizativa real. El resto son entre dos personas que trabajan juntas.
A4: Clasificacion
A5: Tareas sin ninguna dependencia | C5: 8 | D5: Arrancan el dia 1 de su sprint sin esperar a nadie.
A6: Dependen de una tarea propia | C6: 52 | D6: Es el orden del trabajo de una misma persona. No bloquea a nadie.
A7: Dependen de otro integrante, sprint anterior | C7: 20 | D7: Ya estaba entregado y aceptado. No bloquea.
A8: Dependen de otro integrante, mismo sprint | C8: 28 | D8: Se clasifican abajo segun que frontera cruzan.
A9: · dentro de la misma pareja | C9: 11 | D9: Se sientan al lado y coordinan a diario. Riesgo bajo.
A10: · dentro del carril Plataforma | C10: 8 | D10: Dos personas en el mismo carril. Riesgo bajo.
A11: · de Plataforma hacia una pareja | C11: 7 | D11: Frontera real: la pareja consume lo que produce Plataforma.
A12: · entre parejas distintas | C12: 2 | D12: Frontera real. Es lo que el modelo busca minimizar.
A14: De esas 28, 16 tienen solape de fechas. Todas arrancan contra mocks, datos simulados o el emisor de posiciones, y conectan la fuente real al cerrar.
A16: Task ID | B16: Tarea | C16: Resp. | D16: Depende de | E16: Resp. dep. | F16: Frontera | G16: Solape | H16: Estrategia para Evitar Bloqueo
A17: T-101 | B17: Correccion de defectos priorizados | C17: Alex | D17: T-093 | E17: Alejandra | F17: Entre parejas | G17: 14 dias | H17: Se desarrolla contra el mock o los datos simulados del contrato y conecta la fuente real al cerrar la tarea.
A18: T-020 | B18: Cliente HTTP movil contra mocks | C18: Alex | D18: T-012 | E18: Jhon | F18: Entre parejas | G18: 5 dias | H18: El andamiaje del cliente (interceptores, errores) no necesita el mock: se construye primero y se conecta al final.
A19: T-074 | B19: Calculo de posesion | C19: Alejandra | D19: T-058 | E19: Alex | F19: Plataforma -> Producto | G19: 15 dias | H19: Se desarrolla contra el mock o los datos simulados del contrato y conecta la fuente real al cerrar la tarea.
A20: T-092 | B20: Catalogo de reglas en web | C20: Araceli | D20: T-083 | E20: Daniel | F20: Plataforma -> Producto | G20: 8 dias | H20: Se desarrolla contra el mock o los datos simulados del contrato y conecta la fuente real al cerrar la tarea.
A21: T-067 | B21: Asignacion de jugadores a identificadores | C21: Jhon | D21: T-056 | E21: Alex | F21: Plataforma -> Producto | G21: 4 dias | H21: Se desarrolla contra el mock o los datos simulados del contrato y conecta la fuente real al cerrar la tarea.
A22: T-090 | B22: Tarjeta de recomendacion en web | C22: Alejandra | D22: T-082 | E22: Daniel | F22: Plataforma -> Producto | G22: 4 dias | H22: Alejandra construye el componente con recomendaciones simuladas de la forma del contrato, acordado con Daniel el dia 1.
A23: T-012 | B23: Servidor de mocks desde el OpenAPI | C23: Jhon | D23: T-001 | E23: Daniel | F23: Plataforma -> Producto | G23: sin solape | H23: Las rutas y DTOs se bosquejan el dia 1 y se congelan el dia 5. Habilita a los otros cinco: si se atrasa, se atrasa todo.
A24: T-096 | B24: Recepcion de notificaciones push | C24: Araceli | D24: T-087 | E24: Susana | F24: Plataforma -> Producto | G24: sin solape | H24: Se desarrolla contra el mock o los datos simulados del contrato y conecta la fuente real al cerrar la tarea.
A25: T-094 | B25: Recomendaciones en vivo en movil | C25: Alejandra | D25: T-082 | E25: Daniel | F25: Plataforma -> Producto | G25: sin solape | H25: Alejandra usa recomendaciones simuladas. Ambos acuerdan el contrato con Daniel el dia 1.
A26: T-063 | B26: Gestion de modelos en web | C26: Araceli | D26: T-059 | E26: Alex | F26: Dentro de Plataforma | G26: 8 dias | H26: Se desarrolla contra el mock o los datos simulados del contrato y conecta la fuente real al cerrar la tarea.
A27: T-086 | B27: Priorizacion y anti-saturacion | C27: Susana | D27: T-083 | E27: Daniel | F27: Dentro de Plataforma | G27: 8 dias | H27: Se desarrolla contra el mock o los datos simulados del contrato y conecta la fuente real al cerrar la tarea.
... A44: T-052 | B44: Agenda de partidos en movil | C44: Araceli | D44: T-047 | E44: Susana | F44: Misma pareja | G44: sin solape | H44: Se desarrolla contra el mock o los datos simulados del contrato y conecta la fuente real al cerrar la tarea.
A47: Cuellos de botella y camino critico
A48: Task ID | B48: Tarea | C48: Sprint | D48: Resp. | E48: Por que es critica
A49: T-001 | B49: Contratos OpenAPI | C49: S1 | D49: Daniel | E49: Habilita los mocks y con ellos el trabajo paralelo de los otros cinco. Si se atrasa, se atrasa el proyecto entero.
A50: T-009 | B50: Aislamiento multi-club | C50: S1 | D50: Susana | E50: Requisito transversal. Si no esta en el Sprint 1, todos los endpoints posteriores nacen sin proteccion.
A51: T-029 | B51: Homografia y error de reproyeccion | C51: S2 | D51: Jhon | E51: Nucleo geometrico. Si falla, ninguna metrica espacial es valida. Se hace en pareja.
A52: T-034 | B52: Emisor simulado de posiciones | C52: S2 | D52: Alejandra | E52: Desbloquea a las dos parejas un sprint antes de que exista el worker. Segunda tarea anti-bloqueo despues de T-001.
A53: T-055 | B53: Deteccion y seguimiento con YOLO | C53: S3 | D53: Alex | E53: Requiere la maquina con GPU confirmada desde el Sprint 1. Si se atrasa, se entrega sobre video grabado y se documenta.
A54: T-082 | B54: Motor de reglas tacticas | C54: S4 | D54: Daniel | E54: Nucleo del producto. Cuatro tareas de las dos parejas dependen de el. Arranca el dia 1 del sprint y se hace en pareja con Susana.
A55: T-106 | B55: Prueba en cancha con partido real | C55: S4 | D55: Susana | E55: Depende de conseguir cancha y partido: reservar la fecha desde el Sprint 3.

Sheet Resumen
A1: Resumen por Sprint
A2: Los valores se calculan con formulas sobre la hoja Sprint Planning: si cambia una tarea, el resumen se actualiza solo.
A4: Sprint | B4: Dias | C4: Tareas | D4: Daniel | E4: Jhon | F4: Susana | G4: Alex | H4: Alejandra | I4: Araceli | J4: Backend | K4: Web | L4: Movil | M4: Integr. | N4: QA | O4: Prior. Alta | P4: Casos de uso entregados
A5: S1 | B5: 20 | C5: =COUNTIF('Sprint Planning'!$B:$B,$A5) -> 26 | D5: =COUNTIFS('Sprint Planning'!$B:$B,$A5,'Sprint Planning'!$D:$D,"Daniel") -> 5 | E5: =COUNTIFS('Sprint Planning'!$B:$B,$A5,'Sprint Planning'!$D:$D,"Jhon") -> 4 | F5: =COUNTIFS('Sprint Planning'!$B:$B,$A5,'Sprint Planning'!$D:$D,"Susana") -> 5 | G5: =COUNTIFS('Sprint Planning'!$B:$B,$A5,'Sprint Planning'!$D:$D,"Alex") -> 4 | H5: =COUNTIFS('Sprint Planning'!$B:$B,$A5,'Sprint Planning'!$D:$D,"Alejandra") -> 4 | I5: =COUNTIFS('Sprint Planning'!$B:$B,$A5,'Sprint Planning'!$D:$D,"Araceli") -> 4 | J5: =COUNTIFS('Sprint Planning'!$B:$B,$A5,'Sprint Planning'!$H:$H,"Backend") -> 10 | K5: =COUNTIFS('Sprint Planning'!$B:$B,$A5,'Sprint Planning'!$H:$H,"Web") -> 8 | L5: =COUNTIFS('Sprint Planning'!$B:$B,$A5,'Sprint Planning'!$H:$H,"Movil") -> 8 | M5: =COUNTIFS('Sprint Planning'!$B:$B,$A5,'Sprint Planning'!$H:$H,"Integracion") -> 0 | N5: =COUNTIFS('Sprint Planning'!$B:$B,$A5,'Sprint Planning'!$H:$H,"QA") -> 0 | O5: =COUNTIFS('Sprint Planning'!$B:$B,$A5,'Sprint Planning'!$I:$I,"Alta") -> 21 | P5: CU-01, CU-02, CU-03, CU-04, CU-05
A6: S2 | B6: 20 | C6: =COUNTIF('Sprint Planning'!$B:$B,$A6) -> 28 | D6: =COUNTIFS('Sprint Planning'!$B:$B,$A6,'Sprint Planning'!$D:$D,"Daniel") -> 4 | E6: =COUNTIFS('Sprint Planning'!$B:$B,$A6,'Sprint Planning'!$D:$D,"Jhon") -> 5 | F6: =COUNTIFS('Sprint Planning'!$B:$B,$A6,'Sprint Planning'!$D:$D,"Susana") -> 5 | G6: =COUNTIFS('Sprint Planning'!$B:$B,$A6,'Sprint Planning'!$D:$D,"Alex") -> 5 | H6: =COUNTIFS('Sprint Planning'!$B:$B,$A6,'Sprint Planning'!$D:$D,"Alejandra") -> 5 | I6: =COUNTIFS('Sprint Planning'!$B:$B,$A6,'Sprint Planning'!$D:$D,"Araceli") -> 4 | J6: =COUNTIFS('Sprint Planning'!$B:$B,$A6,'Sprint Planning'!$H:$H,"Backend") -> 14 | K6: =COUNTIFS('Sprint Planning'!$B:$B,$A6,'Sprint Planning'!$H:$H,"Web") -> 9 | L6: =COUNTIFS('Sprint Planning'!$B:$B,$A6,'Sprint Planning'!$H:$H,"Movil") -> 5 | M6: =COUNTIFS('Sprint Planning'!$B:$B,$A6,'Sprint Planning'!$H:$H,"Integracion") -> 0 | N6: =COUNTIFS('Sprint Planning'!$B:$B,$A6,'Sprint Planning'!$H:$H,"QA") -> 0 | O6: =COUNTIFS('Sprint Planning'!$B:$B,$A6,'Sprint Planning'!$I:$I,"Alta") -> 19 | P6: CU-09, CU-10, CU-11, CU-12, CU-13, CU-14, CU-15, CU-16, CU-17, CU-18, CU-19, CU-20, CU-21, CU-22, CU-23
A7: S3 | B7: 20 | C7: =COUNTIF('Sprint Planning'!$B:$B,$A7) -> 27 | D7: =COUNTIFS('Sprint Planning'!$B:$B,$A7,'Sprint Planning'!$D:$D,"Daniel") -> 4 | E7: =COUNTIFS('Sprint Planning'!$B:$B,$A7,'Sprint Planning'!$D:$D,"Jhon") -> 5 | F7: =COUNTIFS('Sprint Planning'!$B:$B,$A7,'Sprint Planning'!$D:$D,"Susana") -> 4 | G7: =COUNTIFS('Sprint Planning'!$B:$B,$A7,'Sprint Planning'!$D:$D,"Alex") -> 5 | H7: =COUNTIFS('Sprint Planning'!$B:$B,$A7,'Sprint Planning'!$D:$D,"Alejandra") -> 4 | I7: =COUNTIFS('Sprint Planning'!$B:$B,$A7,'Sprint Planning'!$D:$D,"Araceli") -> 5 | J7: =COUNTIFS('Sprint Planning'!$B:$B,$A7,'Sprint Planning'!$H:$H,"Backend") -> 14 | K7: =COUNTIFS('Sprint Planning'!$B:$B,$A7,'Sprint Planning'!$H:$H,"Web") -> 8 | L7: =COUNTIFS('Sprint Planning'!$B:$B,$A7,'Sprint Planning'!$H:$H,"Movil") -> 5 | M7: =COUNTIFS('Sprint Planning'!$B:$B,$A7,'Sprint Planning'!$H:$H,"Integracion") -> 0 | N7: =COUNTIFS('Sprint Planning'!$B:$B,$A7,'Sprint Planning'!$H:$H,"QA") -> 0 | O7: =COUNTIFS('Sprint Planning'!$B:$B,$A7,'Sprint Planning'!$I:$I,"Alta") -> 21 | P7: CU-24, CU-25, CU-26, CU-27, CU-28, CU-29, CU-30, CU-31, CU-33, CU-34, CU-35, CU-36, CU-37, CU-38, CU-39, CU-40, CU-41, CU-42, CU-43, CU-44, CU-46
A8: S4 | B8: 20 | C8: =COUNTIF('Sprint Planning'!$B:$B,$A8) -> 27 | D8: =COUNTIFS('Sprint Planning'!$B:$B,$A8,'Sprint Planning'!$D:$D,"Daniel") -> 5 | E8: =COUNTIFS('Sprint Planning'!$B:$B,$A8,'Sprint Planning'!$D:$D,"Jhon") -> 4 | F8: =COUNTIFS('Sprint Planning'!$B:$B,$A8,'Sprint Planning'!$D:$D,"Susana") -> 6 | G8: =COUNTIFS('Sprint Planning'!$B:$B,$A8,'Sprint Planning'!$D:$D,"Alex") -> 4 | H8: =COUNTIFS('Sprint Planning'!$B:$B,$A8,'Sprint Planning'!$D:$D,"Alejandra") -> 4 | I8: =COUNTIFS('Sprint Planning'!$B:$B,$A8,'Sprint Planning'!$D:$D,"Araceli") -> 4 | J8: =COUNTIFS('Sprint Planning'!$B:$B,$A8,'Sprint Planning'!$H:$H,"Backend") -> 6 | K8: =COUNTIFS('Sprint Planning'!$B:$B,$A8,'Sprint Planning'!$H:$H,"Web") -> 6 | L8: =COUNTIFS('Sprint Planning'!$B:$B,$A8,'Sprint Planning'!$H:$H,"Movil") -> 4 | M8: =COUNTIFS('Sprint Planning'!$B:$B,$A8,'Sprint Planning'!$H:$H,"Integracion") -> 6 | N8: =COUNTIFS('Sprint Planning'!$B:$B,$A8,'Sprint Planning'!$H:$H,"QA") -> 5 | O8: =COUNTIFS('Sprint Planning'!$B:$B,$A8,'Sprint Planning'!$I:$I,"Alta") -> 18 | P8: CU-45, CU-47, CU-48, CU-49, CU-50, CU-51, CU-52, CU-53, CU-54, CU-55, CU-56
A9: TOTAL | B9: =SUM(B5:B8) -> 80 | C9: =SUM(C5:C8) -> 108 | D9: =SUM(D5:D8) -> 18 | E9: =SUM(E5:E8) -> 18 | F9: =SUM(F5:F8) -> 20 | G9: =SUM(G5:G8) -> 18 | H9: =SUM(H5:H8) -> 17 | I9: =SUM(I5:I8) -> 17 | ... O9: =SUM(O5:O8) -> 79 | P9: 52 casos de uso · sistema completo el 13/11/2026
A12: Analisis de calidad de la planificacion
A13: Modelo elegido | D13: Hibrido. El carril de Plataforma toma lo que no se puede rebanar (contratos, multi-tenant, WebSockets, vision); las parejas se apropian de casos de uso completos de la base de datos a la pantalla.
A14: Por que no 100% vertical | D14: Con 6 personas haciendo rebanadas, los 6 editan el sistema de diseno, el cliente HTTP y las dependencias compartidas al mismo tiempo. Y el worker de vision no es una rebanada: es trabajo especializado de semanas.
A15: Por que no 100% horizontal | D15: Es el modelo donde mueren los proyectos grupales: la API queda lista y nadie hace la pantalla. Con casos de uso, si falta una capa el caso de uso no esta terminado y tiene dueno.
A16: Dependencias | D16: 28 cruzadas dentro del mismo sprint, frente a 33 en la version por tecnologia. Pero solo 9 atraviesan una frontera organizativa real (7 de Plataforma hacia una pareja y 2 entre parejas). Las otras 19 son entre dos personas que trabajan juntas a diario.
A17: Carga por integrante | D17: Entre 17 y 19 tareas cada uno. Dentro de cada sprint, entre 4 y 5 tareas encadenadas, nunca dos a la vez.
A18: Rotacion | D18: Los seis pasan por el carril de Plataforma y nadie repite pareja. Todos trabajan en Backend, Web y Movil a lo largo del proyecto.
A19: Cambio de contexto | D19: La pareja lo reparte: uno toma Backend y Web, el otro Movil. Nadie escribe Python, TypeScript y Dart el mismo dia.
A20: Tareas grandes | D20: T-051 editor de alineacion, T-055 worker de vision y T-082 motor de reglas se revisan a mitad de sprint y se parten si van atrasadas.
A21: Cierre | D21: El Sprint 4 esta partido: desarrollo hasta el 04/11 y estabilizacion pura del 05/11 al 13/11, con la prueba en cancha real al inicio para dejar margen de correccion.
